collective.belowcontentportlets-1.0.0a2-py3.11-nspkg.pth
collective/belowcontentportlets/__init__.py
collective/belowcontentportlets/configure.zcml
collective/belowcontentportlets/interfaces.py
collective/belowcontentportlets/setuphandlers.py
collective/belowcontentportlets/testing.py
collective/belowcontentportlets/viewlet.pt
collective/belowcontentportlets/viewlet.py
collective/belowcontentportlets/locales/__init__.py
collective/belowcontentportlets/locales/collective.abovecontentbodyportlets.pot
collective/belowcontentportlets/locales/plone.pot
collective/belowcontentportlets/locales/update.sh
collective/belowcontentportlets/locales/en/LC_MESSAGES/plone.mo
collective/belowcontentportlets/locales/en/LC_MESSAGES/plone.po
collective/belowcontentportlets/locales/nl/LC_MESSAGES/collective.abovecontentbodyportlets.mo
collective/belowcontentportlets/locales/nl/LC_MESSAGES/collective.abovecontentbodyportlets.po
collective/belowcontentportlets/locales/nl/LC_MESSAGES/plone.mo
collective/belowcontentportlets/locales/nl/LC_MESSAGES/plone.po
collective/belowcontentportlets/profiles/default/browserlayer.xml
collective/belowcontentportlets/profiles/default/metadata.xml
collective/belowcontentportlets/profiles/default/portlets.xml
collective/belowcontentportlets/profiles/uninstall/browserlayer.xml
collective/belowcontentportlets/profiles/uninstall/portlets.xml
collective/belowcontentportlets/tests/__init__.py
collective/belowcontentportlets/tests/test_portlet_manager.py
collective/belowcontentportlets/tests/test_setup.py
collective.belowcontentportlets-1.0.0a2.dist-info/LICENSE.GPL
collective.belowcontentportlets-1.0.0a2.dist-info/LICENSE.rst
collective.belowcontentportlets-1.0.0a2.dist-info/METADATA
collective.belowcontentportlets-1.0.0a2.dist-info/WHEEL
collective.belowcontentportlets-1.0.0a2.dist-info/entry_points.txt
collective.belowcontentportlets-1.0.0a2.dist-info/namespace_packages.txt
collective.belowcontentportlets-1.0.0a2.dist-info/top_level.txt
collective.belowcontentportlets-1.0.0a2.dist-info/RECORD
